{"Personal Info":{"name":"Chryssa M. Nampouri","profession":"Deep Learning Engineer","image":"","email":"chryssanabdmst@gmail.com","location":{"address":"Hoogeweg Str","postalCode":"9746TN","city":"Groningen","region":"Netherlands"}},"work":[{"name":"University Medical Center Groningen (UMCG)","position":"Radiation Oncology Intern","url":"https://www.umcg.nl/","startDate":"2023-03","endDate":"2023-08","summary":"Worked on self-supervised learning methods for 3D medical image analysis using deep neural networks.","highlights":["Medical image analysis","Python","PyTorch","MONAI"]},{"name":"University of Groningen","position":"Teaching Assistant","url":"https://www.rug.nl/","startDate":"2021","endDate":"2023","summary":"Led laboratory tutorials for various courses, addressing student inquiries and preparing assignments and additional instructional materials. Furthermore, I was responsible for providing feedback, grading assignments, and maintaining student records.","highlights":["Introduction to Machine Learning (Undergraduate level)","Introduction to Scientific Computing (Undergraduate level)","Neural Networks and Computational Intelligence (Graduate level)","Pattern Recognition (Graduate level)"]},{"name":"Vodafone Greece","position":"Data Scientist, Vodafone Analytics Team","url":"https://www.vodafone.gr/","startDate":"2019-11","endDate":"2020-07","summary":"Designed and deployed propensity machine learning models to optimize the customer journey experience.","highlights":["Python","TensorFlow","Scikit-learn","PySpark","QGIS"]}],"education":[{"institution":"University of Groningen, Groningen, Netherlands","location":"Groningen, \n Netherlands","url":"https://www.rug.nl/","area":"Computing Science | Intelligent Systems and Visual Computing","studyType":"MSc","startDate":"2021-09","endDate":"2023-08","score":"8.0/10.0","courses":["Neural Networks","Deep Learning","Image Processing","Computer Vision","Pattern Recognition","Scientific Visualization","Computer Graphics"]},{"institution":"Athens University of Economics and Business, Athens, Greece","location":"Athens, \n Greece","url":"https://www.aueb.gr/en","area":"Management Science and Technology | Operations Research and Business Analytics","studyType":"BSc","startDate":"2015-10","endDate":"2020-01","score":"8.1/10.0","courses":["Programming","Algorithms and Data Structures","Stochastic Modeling and Simulation","Combinatorial Optimization","Business Intelligence and Big Data Analytics","Business Analytics and Personalization Technologies","Big Data Management Systems","Data Mining","Machine Learning"]}],"languages":[{"language":"Greek","fluency":"Native speaker","icon":""},{"language":"English","fluency":"Fluent","icon":""},{"language":"German","fluency":"Elementary","icon":""}]}